SeekrAPI-0.0.2.dist-info/DESCRIPTION.rst
SeekrAPI-0.0.2.dist-info/METADATA
SeekrAPI-0.0.2.dist-info/RECORD
SeekrAPI-0.0.2.dist-info/WHEEL
SeekrAPI-0.0.2.dist-info/metadata.json
SeekrAPI-0.0.2.dist-info/top_level.txt
seekrApi/__init__.py
seekrApi/api.py
seekrApi/constant.py
seekrApi/data.py
seekrApi/endpoint.py
seekrApi/render.py
seekrApi/seek.py
seekrApi/data/index.html
seekrApi/data/style.css
