Metadata-Version: 2.0
Name: SeekrAPI
Version: 0.0.2
Summary: Simple documentation for flask api
Home-page: https://github.com/santiagoMeloMedina/Seekr
Author: Santiago Melo Medina
Author-email: santiagodevelopment001@gmail.com
License: UNKNOWN
Platform: UNKNOWN
Classifier: Programming Language :: Python :: 3
Classifier: License :: OSI Approved :: MIT License
Classifier: Operating System :: Unix
Requires-Python: >=3.6
Requires-Dist: Flask (==1.1.2)
